pypi_attestations/__init__.py
pypi_attestations/__main__.py
pypi_attestations/_cli.py
pypi_attestations/_impl.py
pypi_attestations/py.typed
pypi_attestations-0.0.29.dist-info/licenses/LICENSE
pypi_attestations-0.0.29.dist-info/METADATA
pypi_attestations-0.0.29.dist-info/WHEEL
pypi_attestations-0.0.29.dist-info/entry_points.txt
pypi_attestations-0.0.29.dist-info/top_level.txt
pypi_attestations-0.0.29.dist-info/RECORD
