Metadata-Version: 2.4
Name: pypi-attestations
Version: 0.0.29
Summary: A library to convert between Sigstore Bundles and PEP-740 Attestation objects
Author-email: Trail of Bits <opensource@trailofbits.com>
Maintainer-email: PyPI Admins <admin@pypi.org>
License-Expression: Apache-2.0
Project-URL: Homepage, https://pypi.org/project/pypi-attestations
Project-URL: Documentation, https://pypi.github.io/pypi-attestations/
Project-URL: Issues, https://github.com/pypi/pypi-attestations/issues
Project-URL: Source, https://github.com/pypi/pypi-attestations
Classifier: Programming Language :: Python :: 3
Requires-Python: >=3.10
License-File: LICENSE
Requires-Dist: cryptography
Requires-Dist: packaging
Requires-Dist: pyasn1~=0.6
Requires-Dist: pydantic>=2.10.0
Requires-Dist: requests
Requires-Dist: rfc3986
Requires-Dist: sigstore<5.0,>=4.0
Requires-Dist: sigstore-models
Provides-Extra: doc
Requires-Dist: pdoc; extra == "doc"
Provides-Extra: test
Requires-Dist: pytest; extra == "test"
Requires-Dist: pytest-cov; extra == "test"
Requires-Dist: pretend; extra == "test"
Requires-Dist: coverage[toml]; extra == "test"
Provides-Extra: lint
Requires-Dist: ruff~=0.9; extra == "lint"
Requires-Dist: mypy>=1.0; extra == "lint"
Requires-Dist: types-html5lib; extra == "lint"
Requires-Dist: types-requests; extra == "lint"
Requires-Dist: types-toml; extra == "lint"
Requires-Dist: interrogate; extra == "lint"
Requires-Dist: pypi-attestations[test]; extra == "lint"
Provides-Extra: dev
Requires-Dist: pypi-attestations[doc,lint,test]; extra == "dev"
Requires-Dist: build; extra == "dev"
Dynamic: license-file
